currencycloud/__init__.py
currencycloud/client.py
currencycloud/config.py
currencycloud/http.py
currencycloud/version.py
currencycloud/clients/__init__.py
currencycloud/clients/accounts.py
currencycloud/clients/auth.py
currencycloud/clients/balances.py
currencycloud/clients/beneficiaries.py
currencycloud/clients/contacts.py
currencycloud/clients/conversions.py
currencycloud/clients/funding.py
currencycloud/clients/ibans.py
currencycloud/clients/payers.py
currencycloud/clients/payments.py
currencycloud/clients/rates.py
currencycloud/clients/reference.py
currencycloud/clients/reports.py
currencycloud/clients/senders.py
currencycloud/clients/transactions.py
currencycloud/clients/transfers.py
currencycloud/clients/vans.py
currencycloud/clients/withdrawal_accounts.py
currencycloud/errors/__init__.py
currencycloud/errors/api.py
currencycloud/resources/__init__.py
currencycloud/resources/account.py
currencycloud/resources/account_verification.py
currencycloud/resources/balance.py
currencycloud/resources/beneficiary.py
currencycloud/resources/contact.py
currencycloud/resources/conversion.py
currencycloud/resources/funding.py
currencycloud/resources/iban.py
currencycloud/resources/paginated_collection.py
currencycloud/resources/pagination.py
currencycloud/resources/payer.py
currencycloud/resources/payment.py
currencycloud/resources/rate.py
currencycloud/resources/reference.py
currencycloud/resources/report.py
currencycloud/resources/resource.py
currencycloud/resources/sender.py
currencycloud/resources/transaction.py
currencycloud/resources/transfer.py
currencycloud/resources/van.py
currencycloud/resources/withdrawal_account.py
currencycloud/resources/actions/__init__.py
currencycloud/resources/actions/delete.py
currencycloud/resources/actions/update.py
currency_cloud-8.1.0.dist-info/LICENSE.md
currency_cloud-8.1.0.dist-info/METADATA
currency_cloud-8.1.0.dist-info/WHEEL
currency_cloud-8.1.0.dist-info/top_level.txt
currency_cloud-8.1.0.dist-info/RECORD
