Metadata-Version: 2.1
Name: currency_cloud
Version: 8.1.0
Summary: Python SDK for the Currencycloud API.
Home-page: https://github.com/CurrencyCloud/currencycloud-python
Author: Currencycloud
Author-email: sdk@currencycloud.com
License: MIT
Classifier: Development Status :: 5 - Production/Stable
Classifier: Intended Audience :: Developers
Classifier: License :: OSI Approved :: MIT License
Classifier: Operating System :: OS Independent
Classifier: Programming Language :: Python
Classifier: Programming Language :: Python :: 3.8
Classifier: Programming Language :: Python :: 3.9
Classifier: Programming Language :: Python :: 3.10
Classifier: Programming Language :: Python :: 3.11
Classifier: Programming Language :: Python :: 3.12
Classifier: Programming Language :: Python :: Implementation :: PyPy
Classifier: Topic :: Software Development :: Libraries :: Python Modules
License-File: LICENSE.md
Requires-Dist: requests
Requires-Dist: PyYAML
Requires-Dist: deprecation
